cli_elections/__init__.py
cli_elections/main.py
cli_elections/data/__init__.py
cli_elections/data/cnumnuts.csv
cli_elections/data/pscoco.csv
cli_elections/data/psrkl.csv
cli_elections/src/__init__.py
cli_elections/src/downloader.py
cli_elections/src/graph.py
cli_elections/src/parser.py
cli_elections/src/question.py
cli_elections/src/entities/__init__.py
cli_elections/src/entities/district.py
cli_elections/src/entities/party.py
cli_elections/src/entities/village.py
cli_elections-0.3.2.dist-info/METADATA
cli_elections-0.3.2.dist-info/WHEEL
cli_elections-0.3.2.dist-info/entry_points.txt
cli_elections-0.3.2.dist-info/top_level.txt
cli_elections-0.3.2.dist-info/RECORD
